.coveragerc
COPYING
MANIFEST.in
README
setup.cfg
setup.py
tests.krb5.conf
tests.py
tox.ini
kdcproxy/__init__.py
kdcproxy/codec.py
kdcproxy/exceptions.py
kdcproxy/parse_pyasn1.py
kdcproxy.egg-info/PKG-INFO
kdcproxy.egg-info/SOURCES.txt
kdcproxy.egg-info/dependency_links.txt
kdcproxy.egg-info/requires.txt
kdcproxy.egg-info/top_level.txt
kdcproxy/config/__init__.py
kdcproxy/config/mit.py