Metadata-Version: 2.1
Name: kdcproxy
Version: 1.0.0
Summary: A kerberos KDC HTTP proxy WSGI module.
Home-page: http://github.com/latchset/kdcproxy
Author: Nalin Dahyabhai, Nathaniel McCallum, Christian Heimes, Robbie Harwood
Author-email: nalin@redhat.com, npmccallum@redhat.com, cheimes@redhat.com, rharwood@redhat.com
License: MIT
Keywords: krb5 proxy http https kerberos
Platform: UNKNOWN
Classifier: Development Status :: 5 - Production/Stable
Classifier: Environment :: Web Environment
Classifier: Intended Audience :: System Administrators
Classifier: License :: OSI Approved :: MIT License
Classifier: Operating System :: OS Independent
Classifier: Programming Language :: Python :: 3
Classifier: Programming Language :: Python :: 3.6
Classifier: Programming Language :: Python :: 3.7
Classifier: Programming Language :: Python :: 3.8
Classifier: Programming Language :: Python :: 3.9
Classifier: Topic :: Internet :: Proxy Servers
Provides-Extra: test_pep8
Provides-Extra: tests
